Metadata-Version: 2.1
Name: testwordmeaning
Version: 0.0.3
Summary: Recognize whether words are meaningful or not
Home-page: UNKNOWN
Author: moein davarzani
Author-email: moeindavarzani2006@gmail.com
License: MIT
Keywords: testwordmeaning
Platform: UNKNOWN
Classifier: Development Status :: 5 - Production/Stable
Classifier: Intended Audience :: Manufacturing
Classifier: Operating System :: Microsoft :: Windows :: Windows 8
Classifier: License :: OSI Approved :: MIT License
Classifier: Programming Language :: Python :: 3
License-File: LICENSE.txt
